satdata/__init__.py
satdata/aws_goes.py
satdata/cli.py
satdata/utils.py
satdata-0.2.4.dist-info/METADATA
satdata-0.2.4.dist-info/WHEEL
satdata-0.2.4.dist-info/top_level.txt
satdata-0.2.4.dist-info/RECORD
