Metadata-Version: 2.1
Name: satdata
Version: 0.2.4
Summary: Satellite data access from Amazon S3 via python
Home-page: https://github.com/leifdenby/satdata
Author: Leif Denby
Author-email: leifdenby@gmail.com
License: UNKNOWN
Platform: UNKNOWN
Requires-Dist: tqdm
Requires-Dist: s3fs
Requires-Dist: isodate
Provides-Extra: dev
Requires-Dist: pytest ; extra == 'dev'
Requires-Dist: pre-commit ; extra == 'dev'
Requires-Dist: ipython ; extra == 'dev'
Requires-Dist: ipdb ; extra == 'dev'
Provides-Extra: test
Requires-Dist: pytest ; extra == 'test'
